[{
  "label": "United Arab Emirates",
  "code": "AE"
},
  {
    "label": "Argentine",
    "code": "AR"
  },
  {
    "label": "Australia",
    "code": "AU"
  },
  {
    "label": "Austria",
    "code": "AU"
  },
  {
    "label": "Belgium",
    "code": "BE"
  },
  {
    "label": "Bulgaria",
    "code": "BG"
  },
  {
    "label": "Brazil",
    "code": "BR"
  },
  {
    "label": "Canada",
    "code": "CA"
  },
  {
    "label": "United States",
    "code": "US"
  },
  {
    "label": "India",
    "code": "IN"
  }
]